<?xml version="1.0" encoding="windows-1252"?>
<timetable>
  <daysdefs options="canadd" columns="id,days,name,short">
    <daysdef name="Sabtu" short="2" days="100000" id="2"/>
    <daysdef name="Ahad" short="3" days="010000" id="3"/>
    <daysdef name="Senin" short="4" days="001000" id="4"/>
    <daysdef name="Selasa" short="5" days="000100" id="5"/>
    <daysdef name="Rabu" short="6" days="000010" id="6"/>
    <daysdef name="Kamis" short="7" days="000001" id="7"/>
  </daysdefs>
  <periods options="canadd" columns="period,starttime,endtime">
    <period period="1" short="1" starttime="07:30:00" endtime="08:10:00"/>
    <period period="2" short="2" starttime="08:10:00" endtime="08:50:00"/>
    <period period="3" short="3" starttime="08:50:00" endtime="09:30:00"/>
    <period period="4" short="4" starttime="09:30:00" endtime="10:10:00"/>
    <period period="5" short="5" starttime="10:30:00" endtime="11:10:00"/>
    <period period="6" short="6" starttime="11:10:00" endtime="11:50:00"/>
    <period period="7" short="7" starttime="11:50:00" endtime="12:30:00"/>
  </periods>
  <teachers options="canadd" columns="id,name,short,gender,color">
    <teacher id="*1" name="Ainur Rofiq" short="1" gender="L" color="#AC4352"/>
    <teacher id="*2" name="Ahmad Ma'shum" short="2" gender="L" color="#AD2D9B"/>
    <teacher id="*4" name="Muhammadun" short="4" gender="L" color="#E83E83"/>
    <teacher id="*5" name="Moh. In'am Muhlisin" short="5" gender="L" color="#8FB21C"/>
    <teacher id="*9" name="Rozin" short="9" gender="L" color="#CCE4A9"/>
    <teacher id="*11" name="Muhammad Abbad" short="11" gender="L" color="#8249CF"/>
    <teacher id="*14" name="Abdul Ghoffar Rozin" short="14" gender="L" color="#B0A8F5"/>
    <teacher id="*15" name="Ah. Su'udi Romli" short="15" gender="L" color="#7DFAA2"/>
    <teacher id="*16" name="Ahmad Yasir" short="16" gender="L" color="#51EB3A"/>
    <teacher id="*17" name="Ah. Subhan Salim" short="17" gender="L" color="#83B15C"/>
    <teacher id="*18" name="Sidqon Famulaqih" short="18" gender="L" color="#C06B93"/>
    <teacher id="*19" name="Ah. Mu'adz Thohir" short="19" gender="L" color="#32CDF0"/>
    <teacher id="*20" name="Asnawi Rohmat" short="20" gender="L" color="#AC7E44"/>
    <teacher id="*21" name="Ah. Junaidi Muhammadun" short="21" gender="L" color="#1ABE36"/>
    <teacher id="*22" name="Ahmad Nadlif" short="22" gender="L" color="#5CB5D7"/>
    <teacher id="*23" name="Ahmad Nailul Faiz" short="23" gender="L" color="#70593D"/>
    <teacher id="*24" name="Saifurrohman" short="24" gender="L" color="#034919"/>
    <teacher id="*25" name="Ubaidurrohman" short="25" gender="L" color="#FA2A3E"/>
    <teacher id="*26" name="Ahmad Isma'il" short="26" gender="L" color="#E81050"/>
    <teacher id="*27" name="Muhammad Mulin Ni'am" short="27" gender="L" color="#416225"/>
    <teacher id="*28" name="Muh. Ulin Nuha" short="28" gender="L" color="#17BE40"/>
    <teacher id="*29" name="Muh. Wahib Asnawi" short="29" gender="L" color="#367614"/>
    <teacher id="*30" name="Abu Hamid" short="30" gender="L" color="#344CB8"/>
    <teacher id="*31" name="Ah. Irham" short="31" gender="L" color="#741A28"/>
    <teacher id="*32" name="Ah. Nurchafid" short="32" gender="L" color="#7E7896"/>
    <teacher id="*33" name="Ah. Sudar" short="33" gender="L" color="#52C6E7"/>
    <teacher id="*34" name="Ah. Syaerozi" short="34" gender="L" color="#C1482F"/>
    <teacher id="*35" name="Ahmad Mahfudh" short="35" gender="L" color="#DF1D8D"/>
    <teacher id="*36" name="Ahmad Syamsul Ridlwan" short="36" gender="L" color="#8FDE2F"/>
    <teacher id="*37" name="Alaika Muttaqin" short="37" gender="L" color="#2DED96"/>
    <teacher id="*39" name="Ali Ikhwan" short="39" gender="L" color="#7E995B"/>
    <teacher id="*40" name="Arif Rahman" short="40" gender="L" color="#76530B"/>
    <teacher id="*41" name="Faiqotun Nihlah" short="41" gender="P" color="#07EA23"/>
    <teacher id="*42" name="Choiruddin" short="42" gender="L" color="#B44BBF"/>
    <teacher id="*43" name="Arlina Fithroh" short="43" gender="P" color="#3D32A2"/>
    <teacher id="*44" name="Ali Subhan" short="44" gender="L" color="#93C387"/>
    <teacher id="*45" name="Asnunik" short="45" gender="P" color="#DF7711"/>
    <teacher id="*47" name="Nafisah Sahal" short="47" gender="P" color="#921D07"/>
    <teacher id="*48" name="Durroh Muhassonah" short="48" gender="P" color="#EDD29D"/>
    <teacher id="*49" name="Emi Auniyah" short="49" gender="P" color="#908657"/>
    <teacher id="*50" name="Eny Lutfiyana" short="50" gender="P" color="#18EBE0"/>
    <teacher id="*51" name="Faiqotul Hikmah" short="51" gender="P" color="#E48CC5"/>
    <teacher id="*52" name="Fatihuddin" short="52" gender="L" color="#ACE28B"/>
    <teacher id="*53" name="Fauqiyyatul Husna" short="53" gender="P" color="#E98CB6"/>
    <teacher id="*54" name="Fu'adisshobur" short="54" gender="L" color="#CA36AF"/>
    <teacher id="*55" name="Hindun" short="55" gender="P" color="#7D54DC"/>
    <teacher id="*56" name="Fuad Hasan" short="56" gender="L" color="#95DE8F"/>
    <teacher id="*57" name="Asruhah" short="57" gender="P" color="#32AA19"/>
    <teacher id="*58" name="Abd. Afif" short="58" gender="L" color="#15C5DF"/>
    <teacher id="*59" name="Hanifah" short="59" gender="P" color="#892614"/>
    <teacher id="*60" name="Khodijah" short="60" gender="P" color="#168883"/>
    <teacher id="*61" name="Abd. Baqi" short="61" gender="L" color="#D292A3"/>
    <teacher id="*62" name="Mahmudah Nafi'" short="62" gender="P" color="#2B8E98"/>
    <teacher id="*63" name="Abd. Rozaq" short="63" gender="L" color="#E49CE1"/>
    <teacher id="*64" name="Ah. Hadziq" short="64" gender="L" color="#1EF988"/>
    <teacher id="*65" name="Masruroh" short="65" gender="P" color="#AF6E4B"/>
    <teacher id="*66" name="Ah. Ni'am Tamyiz" short="66" gender="L" color="#0F07E1"/>
    <teacher id="*68" name="Ah. Sahal Ali" short="68" gender="L" color="#6EB6BB"/>
    <teacher id="*69" name="Musri'ah" short="69" gender="P" color="#9C6197"/>
    <teacher id="*70" name="Muzdalifah " short="70" gender="P" color="#C53468"/>
    <teacher id="*71" name="Sholihah Muhtar" short="71" gender="P" color="#74C4F8"/>
    <teacher id="*72" name="Ahmad Husnan Basuni" short="72" gender="L" color="#26C609"/>
    <teacher id="*73" name="Ummu Aiman" short="73" gender="P" color="#B024A9"/>
    <teacher id="*74" name="Ahmad Manhajussidad" short="74" gender="L" color="#D566EF"/>
    <teacher id="*75" name="Zulaihah" short="75" gender="P" color="#9EF918"/>
    <teacher id="*76" name="Ahmad Mudhofir" short="76" gender="L" color="#963BC1"/>
    <teacher id="*77" name="Ifiq Shofiyatina" short="77" gender="P" color="#8A6A48"/>
    <teacher id="*78" name="Ali Musyafak" short="78" gender="L" color="#ED8CCC"/>
    <teacher id="*79" name="Intifa'ah" short="79" gender="P" color="#29537F"/>
    <teacher id="*80" name="Farid Ma'ruf Sidiq" short="80" gender="L" color="#AAC07C"/>
    <teacher id="*81" name="Fauzan Kholili" short="81" gender="L" color="#7AB3AA"/>
    <teacher id="*82" name="Islahiyah" short="82" gender="P" color="#D7EBC5"/>
    <teacher id="*83" name="Mas'adah" short="83" gender="P" color="#E96114"/>
    <teacher id="*84" name="Khoirul Asyhar" short="84" gender="L" color="#7BF145"/>
    <teacher id="*85" name="Masyrifah" short="85" gender="P" color="#C01696"/>
    <teacher id="*86" name="Mulyanah" short="86" gender="P" color="#F09B6A"/>
    <teacher id="*87" name="Khotibul Umam" short="87" gender="L" color="#F14F58"/>
    <teacher id="*88" name="Munifah" short="88" gender="P" color="#2FCFAA"/>
    <teacher id="*89" name="Muyassarotul Maisyah" short="89" gender="P" color="#0B436D"/>
    <teacher id="*90" name="Nailin Ni'mah" short="90" gender="P" color="#71A886"/>
    <teacher id="*91" name="Najichatin Niswah" short="91" gender="P" color="#5C6C92"/>
    <teacher id="*92" name="Nasihah" short="92" gender="P" color="#7CDF3E"/>
    <teacher id="*93" name="Noor Azizah" short="93" gender="P" color="#1CF7FB"/>
    <teacher id="*94" name="Nor Maziyah" short="94" gender="P" color="#52EC70"/>
    <teacher id="*95" name="Salmah" short="95" gender="P" color="#C6720E"/>
    <teacher id="*96" name="Siti Fatimatuz Zahro'" short="96" gender="P" color="#6E139C"/>
    <teacher id="*97" name="Siti Khoiriyah" short="97" gender="P" color="#90D61B"/>
    <teacher id="*98" name="Siti Maftuhah Syaerozi" short="98" gender="P" color="#77789B"/>
    <teacher id="*99" name="Siti Makhmudah" short="99" gender="P" color="#903F6D"/>
    <teacher id="*100" name="M. Amiruddin" short="100" gender="L" color="#216D97"/>
    <teacher id="*101" name="Umi Lailatul Maimunah" short="101" gender="P" color="#281CB8"/>
    <teacher id="*102" name="M. Ghufron Wahid" short="102" gender="L" color="#16620C"/>
    <teacher id="*105" name="M. Hasyim Ridlwan" short="105" gender="L" color="#0098A4"/>
    <teacher id="*106" name="Laila Fathiyyah" short="106" gender="P" color="#A39A7C"/>
    <teacher id="*107" name="Maslihan M. Ali" short="107" gender="L" color="#A7822F"/>
    <teacher id="*108" name="Milhatin Syirfah" short="108" gender="P" color="#168F17"/>
    <teacher id="*109" name="Masrukhan Selamet" short="109" gender="L" color="#99B65F"/>
    <teacher id="*110" name="Mu'nisatin Kamilah" short="110" gender="P" color="#7121CD"/>
    <teacher id="*111" name="Mohammad Agus Jauhari" short="111" gender="L" color="#06A929"/>
    <teacher id="*112" name="Muhammad Zaim" short="112" gender="L" color="#16F2F5"/>
    <teacher id="*113" name="Muslikhatul Ummah" short="113" gender="P" color="#BC72C7"/>
    <teacher id="*114" name="Noor Chudriyatin" short="114" gender="P" color="#0E12D6"/>
    <teacher id="*115" name="Muhammadun" short="115" gender="L" color="#1A98F1"/>
    <teacher id="*116" name="Siti Munawaroh" short="116" gender="P" color="#F61D4A"/>
    <teacher id="*117" name="Muharror Afif" short="117" gender="L" color="#420F84"/>
    <teacher id="*118" name="Nur Dihyah" short="118" gender="L" color="#FF6AE1"/>
    <teacher id="*119" name="Saiful Akhyar" short="119" gender="L" color="#1841F1"/>
    <teacher id="*120" name="Santoso" short="120" gender="L" color="#C4C34F"/>
    <teacher id="*121" name="Sholihul Hadi" short="121" gender="L" color="#AD02F3"/>
    <teacher id="*122" name="Sulkan" short="122" gender="L" color="#49AF52"/>
    <teacher id="*123" name="Syafi'I Abdan" short="123" gender="L" color="#14A201"/>
    <teacher id="*124" name="Wakhrodi" short="124" gender="L" color="#B03A9D"/>
    <teacher id="*125" name="Ibrohim Ms" short="125" gender="L" color="#DC7D91"/>
    <teacher id="*126" name="Khotibul Umam Zainuddin" short="126" gender="L" color="#1B6657"/>
    <teacher id="*127" name="M. Alauddin Lutfi" short="127" gender="L" color="#A88126"/>
    <teacher id="*128" name="Marzuqi Abdul Bari" short="128" gender="L" color="#F62B8D"/>
    <teacher id="*129" name="Maskur" short="129" gender="L" color="#883300"/>
    <teacher id="*130" name="Miftakhul Munif" short="130" gender="L" color="#B5F580"/>
    <teacher id="*131" name="Isfanda" short="131" gender="L" color="#D15E59"/>
    <teacher id="*132" name="Moh. Lutfi" short="132" gender="L" color="#2E0218"/>
    <teacher id="*133" name="Moh. Ulil Albab" short="133" gender="L" color="#EC5656"/>
    <teacher id="*134" name="Mu'adz Syam" short="134" gender="L" color="#3B9DF8"/>
    <teacher id="*135" name="Mohammad Alex Fawzi" short="135" gender="L" color="#17E4C7"/>
    <teacher id="*136" name="Muhammad Fatah" short="136" gender="L" color="#BD590C"/>
    <teacher id="*137" name="Muhammad Faiq" short="137" gender="L" color="#D7B65D"/>
    <teacher id="*138" name="Muhammad Misbah Munir" short="138" gender="L" color="#181432"/>
    <teacher id="*139" name="Ahmad Lutfi" short="139" gender="L" color="#9E28D8"/>
    <teacher id="*144" name="Muhammad Riza Nor Rohman" short="144" gender="L" color="#D25F2E"/>
    <teacher id="*145" name="Muhammad Sabiq" short="145" gender="L" color="#A76195"/>
    <teacher id="*146" name="Muhammad Zaenuri" short="146" gender="L" color="#B4C128"/>
    <teacher id="*147" name="Ahmad Miftahus Syifa`" short="147" gender="L" color="#6B341E"/>
    <teacher id="*148" name="Muhtadi" short="148" gender="L" color="#8F04F7"/>
    <teacher id="*149" name="Muhammad Sulton" short="149" gender="L" color="#054DC1"/>
    <teacher id="*150" name="Saifur Rosyid" short="150" gender="L" color="#83E43D"/>
    <teacher id="*151" name="Taufiqur Rohman" short="151" gender="L" color="#2E0CE4"/>
    <teacher id="*152" name="Ali Widiantoro" short="152" gender="L" color="#A8A725"/>
    <teacher id="*153" name="Ainur Rofiq" short="153" gender="L" color="#97B42E"/>
    <teacher id="*155" name="Ahmad Ma'shum" short="155" gender="L" color="#3B7F4E"/>
    <teacher id="*158" name="Sukardi" short="158" gender="L" color="#34FA7E"/>
    <teacher id="*159" name="Hasyim" short="159" gender="L" color="#B8BCB2"/>
    <teacher id="*160" name="Tarwiji" short="160" gender="L" color="#CF55DB"/>
    <teacher id="*161" name="Zainuri" short="161" gender="L" color="#6241F0"/>
    <teacher id="*165" name="Muhammadun " short="165" gender="L" color="#A0C16A"/>
    <teacher id="*166" name="Masrukhan" short="166" gender="L" color="#CF804F"/>
    <teacher id="*167" name="Mohammad Azwar Anas" short="167" gender="L" color="#81A232"/>
    <teacher id="*169" name="Moch Syams El Ma'arif" short="169" gender="L" color="#D41D8A"/>
    <teacher id="*170" name="Noor Hakim" short="170" gender="L" color="#5A05E3"/>
    <teacher id="*171" name="Jamaluddin Nur" short="171" gender="L" color="#E1EADC"/>
    <teacher id="*173" name="Muh. In'am Muhlisin" short="173" gender="L" color="#CF8008"/>
    <teacher id="*175" name="M. Dian Arifuddin" short="175" gender="L" color="#EB2AE9"/>
    <teacher id="*176" name="Rozin" short="176" gender="L" color="#458723"/>
    <teacher id="*177" name="Ahmad Fathi Nashih" short="177" gender="L" color="#E8D801"/>
    <teacher id="*178" name="Fachrur Rozi" short="178" gender="L" color="#62208C"/>
    <teacher id="*179" name="Moh. Ulin Nuha Annabil" short="179" gender="L" color="#BD8762"/>
  </teachers>
  <classes options="canadd" columns="id,name,short,classroomids,teacherid,grade">
    <class id="*14" name="1 Aliyah E Banin" short="14" teacherid="" classroomids="" grade=""/>
    <class id="*15" name="1 Aliyah D Banin" short="15" teacherid="" classroomids="" grade=""/>
    <class id="*16" name="1 Aliyah C Banin" short="16" teacherid="" classroomids="" grade=""/>
    <class id="*17" name="1 Aliyah B Banin" short="17" teacherid="" classroomids="" grade=""/>
    <class id="*18" name="1 Aliyah A Banin" short="18" teacherid="" classroomids="" grade=""/>
    <class id="*6" name="2 Aliyah A Banin" short="6" teacherid="" classroomids="" grade=""/>
    <class id="*7" name="2 Aliyah B Banin" short="7" teacherid="" classroomids="" grade=""/>
    <class id="*8" name="2 Aliyah C Banin" short="8" teacherid="" classroomids="" grade=""/>
    <class id="*19" name="2 Aliyah D Banin" short="19" teacherid="" classroomids="" grade=""/>
    <class id="*2" name="3 Aliyah A Banin" short="2" teacherid="" classroomids="" grade=""/>
    <class id="*3" name="3 Aliyah B Banin" short="3" teacherid="" classroomids="" grade=""/>
    <class id="*4" name="3 Aliyah C Banin" short="4" teacherid="" classroomids="" grade=""/>
    <class id="*5" name="3 Aliyah D Banin" short="5" teacherid="" classroomids="" grade=""/>
  </classes>
  <subjects options="canadd" columns="id,name,short">
    <subject id="*AL-FQiH" name="Fiqih Tahrir" short="AL-FQiH"/>
    <subject id="*AL-FSLTN" name="FASHOLATAN" short="AL-FSLTN"/>
    <subject id="*AL-NHW" name="Nahwu Alfiyah" short="AL-NHW"/>
    <subject id="*AL-ALQN" name="AL QUR'AN" short="AL-ALQN"/>
    <subject id="*AL-TQRIB" name="TAQRIB" short="AL-TQRIB"/>
  </subjects>
</timetable>
